sklearn_dual/conftest.py
sklearn_dual/_isotonic.cpython-313-darwin.so
sklearn_dual/multiclass.py
sklearn_dual/_isotonic.pyx
sklearn_dual/kernel_approximation.py
sklearn_dual/random_projection.py
sklearn_dual/isotonic.py
sklearn_dual/multioutput.py
sklearn_dual/__init__.py
sklearn_dual/_built_with_meson.py
sklearn_dual/kernel_ridge.py
sklearn_dual/_distributor_init.py
sklearn_dual/_min_dependencies.py
sklearn_dual/meson.build
sklearn_dual/naive_bayes.py
sklearn_dual/pipeline.py
sklearn_dual/discriminant_analysis.py
sklearn_dual/exceptions.py
sklearn_dual/_config.py
sklearn_dual/dummy.py
sklearn_dual/base.py
sklearn_dual/calibration.py
sklearn_dual/tree/_utils.pyx
sklearn_dual/tree/_tree.pxd
sklearn_dual/tree/_splitter.cpython-313-darwin.so
sklearn_dual/tree/_partitioner.pxd
sklearn_dual/tree/_criterion.cpython-313-darwin.so
sklearn_dual/tree/_criterion.pyx
sklearn_dual/tree/_tree.cpython-313-darwin.so
sklearn_dual/tree/_splitter.pyx
sklearn_dual/tree/__init__.py
sklearn_dual/tree/_partitioner.cpython-313-darwin.so
sklearn_dual/tree/meson.build
sklearn_dual/tree/_export.py
sklearn_dual/tree/_utils.cpython-313-darwin.so
sklearn_dual/tree/_splitter.pxd
sklearn_dual/tree/_criterion.pxd
sklearn_dual/tree/_reingold_tilford.py
sklearn_dual/tree/_partitioner.pyx
sklearn_dual/tree/_classes.py
sklearn_dual/tree/_utils.pxd
sklearn_dual/tree/_tree.pyx
sklearn_dual/tree/tests/test_monotonic_tree.py
sklearn_dual/tree/tests/test_tree.py
sklearn_dual/tree/tests/test_reingold_tilford.py
sklearn_dual/tree/tests/__init__.py
sklearn_dual/tree/tests/test_export.py
sklearn_dual/metrics/_scorer.py
sklearn_dual/metrics/_classification.py
sklearn_dual/metrics/_base.py
sklearn_dual/metrics/_pairwise_fast.cpython-313-darwin.so
sklearn_dual/metrics/_regression.py
sklearn_dual/metrics/_dist_metrics.pyx.tp
sklearn_dual/metrics/_dist_metrics.pxd.tp
sklearn_dual/metrics/__init__.py
sklearn_dual/metrics/meson.build
dualxda_skl-1.6.0.dev0.dist-info/RECORD
dualxda_skl-1.6.0.dev0.dist-info/WHEEL
dualxda_skl-1.6.0.dev0.dist-info/COPYING
dualxda_skl-1.6.0.dev0.dist-info/METADATA
