Metadata-Version: 2.1
Name: dualxda_skl
Version: 1.6.0.dev0
Summary: A fork of scikit-learn that lets the user reach the dual variables for the LinearSVC class.
Maintainer-Email: =?utf-8?q?Galip_=C3=9Cmit_Yolcu?= <galip.uemit.yolcu@fraunhofer.de>
License: BSD 3-Clause License
Requires-Python: >=3.9
Requires-Dist: numpy>=1.19.5
Requires-Dist: scipy>=1.6.0
Requires-Dist: joblib>=1.2.0
Requires-Dist: threadpoolctl>=3.1.0
